processor/sail-core/simulation/branch_pred.v
module branch_predictor (
    input clk,
    input [31:0] fetch_pc,
    output reg [31:0] branch_addr,
    output reg prediction,
    input update_en,
    input [31:0] update_pc,
    input [31:0] update_target
);
    parameter BTB_SIZE = 16;
    parameter ASSOC = 4;

    reg [31:0] btb_pc [0:BTB_SIZE-1][0:ASSOC-1];
    reg [31:0] btb_target [0:BTB_SIZE-1][0:ASSOC-1];
    reg btb_valid [0:BTB_SIZE-1][0:ASSOC-1];
    reg [1:0] lru_counter [0:BTB_SIZE-1];

    integer w;              // Loop/index variable
    integer lru_way;        // LRU way to replace
    integer match_found;    // Match detection flag

    always @(posedge clk) begin
        if (update_en) begin
            match_found = 0;
            for (w = 0; w < ASSOC; w = w + 1) begin
                if (btb_valid[update_pc[5:2]][w] && btb_pc[update_pc[5:2]][w] == update_pc) begin
                    btb_target[update_pc[5:2]][w] <= update_target;
                    match_found = 1;
                end
            end
            if (!match_found) begin
                lru_way = lru_counter[update_pc[5:2]];
                btb_pc[update_pc[5:2]][lru_way] <= update_pc;
                btb_target[update_pc[5:2]][lru_way] <= update_target;
                btb_valid[update_pc[5:2]][lru_way] <= 1'b1;
                lru_counter[update_pc[5:2]] <= (lru_counter[update_pc[5:2]] + 1) % ASSOC;
            end
        end
    end

    reg hit;
    reg [31:0] predicted_target;
    always @(*) begin
        hit = 1'b0;
        predicted_target = fetch_pc + 4;
        for (w = 0; w < ASSOC; w = w + 1) begin
            if (btb_valid[fetch_pc[5:2]][w] && btb_pc[fetch_pc[5:2]][w] == fetch_pc) begin
                hit = 1'b1;
                predicted_target = btb_target[fetch_pc[5:2]][w];
            end
        end
    end

    always @(*) begin
        branch_addr = predicted_target;
        prediction = hit;
    end
endmodule

processor/sail-core/simulation/branch_pred_tb.v
`timescale 1ns/1ps

module tb_branch_predictor;

    reg clk;
    reg [31:0] fetch_pc;
    reg update_en;
    reg [31:0] update_pc;
    reg [31:0] update_target;
    wire [31:0] branch_addr;
    wire prediction;
    integer i;
    
    // Instantiate the branch predictor
    branch_predictor uut (
        .clk(clk),
        .fetch_pc(fetch_pc),
        .branch_addr(branch_addr),
        .prediction(prediction),
        .update_en(update_en),
        .update_pc(update_pc),
        .update_target(update_target)
    );

    // Clock generation
    initial begin
        clk = 0;
        forever #5 clk = ~clk;  // 100MHz clock (period 10ns)
        
    end

    initial begin
        // Initialize signals
        fetch_pc = 0;
        update_en = 0;
        update_pc = 0;
        update_target = 0;

        // Add waveform dump for GTKWave
        $dumpfile("branch_predictor_tb.vcd");
        $dumpvars(0, tb_branch_predictor);

        // Test 1: Predict for PC not in BTB
        #10 fetch_pc = 32'h00001000;  // Prediction should be PC+4
        #10;

        // Test 2: Add a branch entry at 0x1000 -> 0x2000
        update_pc = 32'h00001000;
        update_target = 32'h00002000;
        update_en = 1;
        #10 update_en = 0;

        // Test 3: Predict for 0x1000 (should hit with target 0x2000)
        #10 fetch_pc = 32'h00001000;
        #10;

        // Test 4: Add another entry at 0x3000 -> 0x4000
        update_pc = 32'h00003000;
        update_target = 32'h00004000;
        update_en = 1;
        #10 update_en = 0;

        // Test 5: Predict for 0x3000
        #10 fetch_pc = 32'h00003000;
        #10;

        // Test 6: Predict for 0x5000 (no entry, predict PC+4)
        #10 fetch_pc = 32'h00005000;
        #10;

        // Test 7: Update same PC 0x1000 with new target 0x2100 (overwrite)
        update_pc = 32'h00001000;
        update_target = 32'h00002100;
        update_en = 1;
        #10 update_en = 0;

        // Predict for 0x1000 (should reflect new target 0x2100)
        #10 fetch_pc = 32'h00001000;
        #10;

        // Test 8: Insert multiple entries to test LRU replacement
        for (i = 0; i < 5; i = i + 1) begin
            update_pc = 32'h00006000 + (i * 4);
            update_target = 32'h00007000 + (i * 4);
            update_en = 1;
            #10 update_en = 0;
        end

        // Predict for the first inserted entry (might be replaced if BTB is small)
        #10 fetch_pc = 32'h00006000;
        #10;

        // Done
        #50 $finish;
    end

    // Monitor output
    initial begin
        $monitor("Time=%0t | fetch_pc=0x%08h | prediction=%b | branch_addr=0x%08h | update_en=%b update_pc=0x%08h update_target=0x%08h",
                  $time, fetch_pc, prediction, branch_addr, update_en, update_pc, update_target);
    end

endmodule

processor/sail-core/simulation/branch_predictor_tb.vcd
$date
	Wed May 28 21:41:53 2025
$end
$version
	Icarus Verilog
$end
$timescale
	1ps
$end
$scope module tb_branch_predictor $end
$var wire 1 ! prediction $end
$var wire 32 " branch_addr [31:0] $end
$var reg 1 # clk $end
$var reg 32 $ fetch_pc [31:0] $end
$var reg 1 % update_en $end
$var reg 32 & update_pc [31:0] $end
$var reg 32 ' update_target [31:0] $end
$var integer 32 ( i [31:0] $end
$scope module uut $end
$var wire 1 # clk $end
$var wire 32 ) fetch_pc [31:0] $end
$var wire 1 % update_en $end
$var wire 32 * update_pc [31:0] $end
$var wire 32 + update_target [31:0] $end
$var parameter 32 , ASSOC $end
$var parameter 32 - BTB_SIZE $end
$var reg 32 . branch_addr [31:0] $end
$var reg 1 / hit $end
$var reg 32 0 predicted_target [31:0] $end
$var reg 1 ! prediction $end
$var integer 32 1 lru_way [31:0] $end
$var integer 32 2 match_found [31:0] $end
$var integer 32 3 w [31:0] $end
$upscope $end
$upscope $end
$enddefinitions $end
$comment Show the parameter values. $end
$dumpall
b10000 -
b100 ,
$end
#0
$dumpvars
b100 3
bx 2
bx 1
b100 0
0/
b100 .
b0 +
b0 *
b0 )
bx (
b0 '
b0 &
0%
b0 $
0#
b100 "
0!
$end
#5000
1#
#10000
b1000000000100 "
b1000000000100 .
b100 3
b1000000000100 0
0#
b1000000000000 $
b1000000000000 )
#15000
1#
#20000
0#
1%
b10000000000000 '
b10000000000000 +
b1000000000000 &
b1000000000000 *
#25000
b0xx 1
b100 3
b0 2
1#
#30000
0#
0%
#35000
1#
#40000
0#
#45000
1#
#50000
0#
1%
b100000000000000 '
b100000000000000 +
b11000000000000 &
b11000000000000 *
#55000
b100 3
1#
#60000
0#
0%
#65000
1#
#70000
b11000000000100 "
b11000000000100 .
b100 3
b11000000000100 0
0#
b11000000000000 $
b11000000000000 )
#75000
1#
#80000
0#
#85000
1#
#90000
b101000000000100 "
b101000000000100 .
b100 3
b101000000000100 0
0#
b101000000000000 $
b101000000000000 )
#95000
1#
#100000
0#
1%
b10000100000000 '
b10000100000000 +
b1000000000000 &
b1000000000000 *
#105000
b100 3
1#
#110000
0#
0%
#115000
1#
#120000
b1000000000100 "
b1000000000100 .
b100 3
b1000000000100 0
0#
b1000000000000 $
b1000000000000 )
#125000
1#
#130000
0#
1%
b111000000000000 '
b111000000000000 +
b110000000000000 &
b110000000000000 *
b0 (
#135000
b100 3
1#
#140000
0#
b111000000000100 '
b111000000000100 +
b110000000000100 &
b110000000000100 *
b1 (
1%
#145000
b100 3
1#
#150000
0#
b111000000001000 '
b111000000001000 +
b110000000001000 &
b110000000001000 *
b10 (
1%
#155000
b100 3
1#
#160000
0#
b111000000001100 '
b111000000001100 +
b110000000001100 &
b110000000001100 *
b11 (
1%
#165000
b100 3
1#
#170000
0#
b111000000010000 '
b111000000010000 +
b110000000010000 &
b110000000010000 *
b100 (
1%
#175000
b100 3
1#
#180000
0#
b101 (
0%
#185000
1#
#190000
b110000000000100 "
b110000000000100 .
b100 3
b110000000000100 0
0#
b110000000000000 $
b110000000000000 )
